{
  "companyName": "Roblox",
  "jobTitle": "Core Engine Developer - Systems (C++)",
  "jobLocation": ["San Mateo CA"],
  "jobType": "Full Time",
  "jobResponsibilities": [

      "引擎网络团队负责确保游戏状态能够在所有玩家之间高效、可靠地传递，从而把玩家连接成一个整体的游戏世界。",
      "作为首席网络传输工程师，帮助玩家体验一个“几乎同步”的多人游戏环境。",
      "网络系统之于游戏平台，正如神经系统之于人体，负责协调和同步各个部分的运作。",
      "参与并影响游戏平台的各个层面。",
      "实现 Roblox 各个组件之间的实时通信，保障整体体验的流畅性与一致性。"
    ],
  "candidateQualifications": {
    "basicQualifications": [
      "4 年以上游戏网络方向的软件工程经验，背景来自游戏引擎或游戏工作室",
      "对网络协议栈有深入理解，并热衷于使用和参与开源项目",
      "具备扎实的系统级 C++ 编程经验，对 CPU 在执行智能指针、模板、虚函数以及结构化/原始内存操作时的底层行为有深入理解与兴趣",
      "熟悉 Linux 网络相关机制，对常见网络协议有良好掌握",
      "对网络通信中的每一毫秒高度敏感，清楚性能开销的来源，并具备减少浪费的能力",
      "理解代码执行完成后在操作系统层面所触发的具体行为"
    ],
    "preferredQualifications": [
      "参与过高性能用户态网络协议栈的开发，能够解决客户端 / 服务器环境下的规模、性能、延迟和吞吐量问题",
      "有在超大规模多线程分布式系统中的工作经验，该系统连接着全球数以百万计的用户",
      "有在 Roblox 支持的各类设备上工作的经验，包括桌面端、移动端以及主机平台",
      "参与过游戏引擎相关开发，对游戏引擎的整体工作机制有深入理解"
    ]
  },
  "salary": ["$195,780.00 - $242,100.00/year"],
  "benefits": [
      "覆盖全面的医疗、牙科和视力保险",
      "每年提供 25 次心理健康辅导或心理治疗服务",
      "提供最高 5 万美元的终身福利，用于生育、收养相关服务",
      "401(k) 退休金计划：公司按 1:1 匹配员工缴纳金额，最高可达 IRS 规定递延上限的 50%",
      "员工股票购买计划：享受 15% 折扣，并提供 24 个月回溯期（lookback） 用于计算购股价格",
      "为豁免员工（exempt employees）提供灵活的带薪休假（Flexible PTO）"
    ],
  "jobLink": "https://careers.roblox.com/jobs/7561736",
  "notes": ""
}